libname/__init__.py
libname/hello.py
vidstrGeam-0.0.13.dist-info/METADATA
vidstrGeam-0.0.13.dist-info/WHEEL
vidstrGeam-0.0.13.dist-info/top_level.txt
vidstrGeam-0.0.13.dist-info/RECORD
