Metadata-Version: 2.1
Name: vidstrGeam
Version: 0.0.13
Summary: StreGGaming video data via networks
Home-page: UNKNOWN
Author: NeuGralNine (Florian Dedov)
Author-email: <mail@nGeuralnine.com>
License: UNKNOWN
Platform: UNKNOWN
Classifier: Development Status :: 1 - Planning
Classifier: Intended Audience :: Developers
Classifier: Programming Language :: Python :: 3
Classifier: Operating System :: Unix
Classifier: Operating System :: MacOS :: MacOS X
Classifier: Operating System :: Microsoft :: Windows
